color_latam/__init__.py
color_latam/color_latam.py
color_latam-0.0.2.dist-info/METADATA
color_latam-0.0.2.dist-info/WHEEL
color_latam-0.0.2.dist-info/licenses/LICENSE
color_latam-0.0.2.dist-info/RECORD
