Metadata-Version: 2.1
Name: color_latam
Version: 0.0.2
Summary: Libreria que cambia el color del texto en español
Project-URL: Homepage, https://github.com/israelubeda/color_es
Project-URL: Bug Tracker, https://github.com/israelubeda/color_es
Author-email: Israel Ubeda <israel.ubedabravo@gmail.com>
License-File: LICENSE
Classifier: License :: OSI Approved :: MIT License
Classifier: Operating System :: OS Independent
Classifier: Programming Language :: Python :: 3
Requires-Python: >=3.7
